dactyl/__init__.py
dactyl/cli.py
dactyl/common.py
dactyl/config.py
dactyl/dactyl_build.py
dactyl/dactyl_link_checker.py
dactyl/dactyl_style_checker.py
dactyl/default-config.yml
dactyl/filter_add_version.py
dactyl/filter_badges.py
dactyl/filter_buttonize.py
dactyl/filter_callouts.py
dactyl/filter_demote_headers.py
dactyl/filter_external_links.py
dactyl/filter_link_replacement.py
dactyl/filter_markdown_in_divs.py
dactyl/filter_multicode_tabs.py
dactyl/filter_remove_doctoc.py
dactyl/filter_standardize_header_ids.py
dactyl/filter_xrefs.py
dactyl/http_constants.py
dactyl/jinja_loaders.py
dactyl/openapi.py
dactyl/page.py
dactyl/style_report.py
dactyl/target.py
dactyl/version.py
dactyl/watch_handler.py
dactyl/words.txt
dactyl/templates/404.html
dactyl/templates/README.md
dactyl/templates/algolia-docsearch.html
dactyl/templates/base.html
dactyl/templates/breadcrumbs.html
dactyl/templates/children.html
dactyl/templates/doc.html
dactyl/templates/footer.html
dactyl/templates/github-edit.html
dactyl/templates/google-search.html
dactyl/templates/header.html
dactyl/templates/landing.html
dactyl/templates/language-dropdown.html
dactyl/templates/language-nav.html
dactyl/templates/page-toc.html
dactyl/templates/pdf-cover.html
dactyl/templates/redirect.html
dactyl/templates/simple.html
dactyl/templates/template-es.json
dactyl/templates/template-openapi_data_type.md
dactyl/templates/template-openapi_data_types_toc.md
dactyl/templates/template-openapi_endpoint.md
dactyl/templates/template-openapi_endpoint_tag_toc.md
dactyl/templates/template-openapi_endpoint_toc.md
dactyl/templates/template-sitemap.txt
dactyl/templates/tree-nav.html
dactyl-0.15.4.dist-info/LICENSE
dactyl-0.15.4.dist-info/METADATA
dactyl-0.15.4.dist-info/WHEEL
dactyl-0.15.4.dist-info/entry_points.txt
dactyl-0.15.4.dist-info/top_level.txt
dactyl-0.15.4.dist-info/RECORD
