Metadata-Version: 2.1
Name: dactyl
Version: 0.15.4
Summary: Tools to generate documentation.
Home-page: https://github.com/ripple/dactyl
Author: Ripple
Author-email: rome@ripple.com
License: MIT
Keywords: documentation
Classifier: Development Status :: 3 - Alpha
Classifier: Environment :: Console
Classifier: Intended Audience :: End Users/Desktop
Classifier: License :: OSI Approved :: MIT License
Classifier: Operating System :: POSIX
Classifier: Programming Language :: Python :: 3
Classifier: Programming Language :: Python :: 3.5
Classifier: Topic :: Utilities
Classifier: Topic :: Documentation
License-File: LICENSE
Requires-Dist: argparse
Requires-Dist: beautifulsoup4
Requires-Dist: jinja2 (>=2.11)
Requires-Dist: Markdown (>=3.0.1)
Requires-Dist: ruamel.yaml
Requires-Dist: requests
Requires-Dist: watchdog
Requires-Dist: textstat
Requires-Dist: pyspellchecker
Requires-Dist: pygments
